libpymcr/IPythonMagics.py
libpymcr/Matlab.py
libpymcr/MatlabProxyObject.py
libpymcr/__init__.py
libpymcr/_libpymcr.cp310-win_amd64.pyd
libpymcr/_version.py
libpymcr/utils.py
libpymcr/scripts/matlab2python.py
libpymcr/scripts/parseclass.m
libpymcr-0.2.1.dist-info/LICENSE
libpymcr-0.2.1.dist-info/METADATA
libpymcr-0.2.1.dist-info/WHEEL
libpymcr-0.2.1.dist-info/entry_points.txt
libpymcr-0.2.1.dist-info/top_level.txt
libpymcr-0.2.1.dist-info/RECORD
